dpy_docs/__init__.py
dpy_docs/main.py
dpy_docs-0.1.2.dist-info/WHEEL
dpy_docs-0.1.2.dist-info/METADATA
dpy_docs-0.1.2.dist-info/RECORD
