Metadata-Version: 2.1
Name: dpy-docs
Version: 0.1.2
Summary: A simple, lightweight tool used for documemting your discord.py commands
Home-page: https://github.com/ChiliMX/dpy-docs
License: MIT
Author: ChiliMX
Author-email: chili.dev@gmail.com
Requires-Python: >=3.9,<4.0
Classifier: License :: OSI Approved :: MIT License
Classifier: Programming Language :: Python :: 3
Classifier: Programming Language :: Python :: 3.9
Requires-Dist: aiofiles (>=0.7.0,<0.8.0)
Requires-Dist: discord.py (>=1.7.3,<2.0.0)
Project-URL: Repository, https://github.com/ChiliMX/dpy-docs
